Maxl/__init__.py
Maxl/main.py
maxl-0.1.dist-info/METADATA
maxl-0.1.dist-info/WHEEL
maxl-0.1.dist-info/top_level.txt
maxl-0.1.dist-info/RECORD
