Metadata-Version: 2.4
Name: Maxl
Version: 0.1
Summary: Library for finding the max in a list.
Home-page: https://github.com/Yaraaa2650/Maxl
Author: Yaroslava
Author-email: yarash0607@gmail.com
Classifier: Programming Language :: Python :: 3
Classifier: License :: OSI Approved :: MIT License
Classifier: Operating System :: OS Independent
Requires-Python: >=3.6
Dynamic: author
Dynamic: author-email
Dynamic: classifier
Dynamic: description
Dynamic: description-content-type
Dynamic: home-page
Dynamic: requires-python
Dynamic: summary
